Metadata-Version: 2.1
Name: omniplex
Version: 0.1.1
Summary: "Omni-plex Versatile Data Management for Rapid AI Prototyping and Research"
License: MIT
Classifier: Programming Language :: Python :: 3.8
Provides-Extra: test
License-File: LICENSE
